Workbook
Name aporte: Calculadora!$C$10
Name investimento: Calculadora!$C$25
Name patrimonio: Calculadora!$C$13
Name qtd_anos: Calculadora!$C$11
Name rendimento_carteira: Calculadora!$C$6
Name taxa_mensal: Calculadora!$C$12
Name tipo_perfil: Calculadora!$C$24

Sheet Calculadora
B4: Configurações
B5: Salário | C5: 5000 | D5: Defina o valor do seu salário
B6: Rendimento Carteira | C6: 0.006
B7: Sugestão de investimento | C7: =C5*0.3 -> 1500 | D7: Saiba qual seria o valor sugerido de investimento com base em seu salário (aprox.30%)
B9: INVESTIMENTO MENSAL
B10: Quanto investir por mês? | C10: 750 | D10: Defina um valor de aporte mensal
B11: Por Quantos Anos? | C11: 5 | D11: Defina um período de aplicações
B12: Taxa de Rendimento mensal? | C12: 0.0108 | D12: Defina um valor de rendimento mensal
B13: Patrimônio acumulado? | C13: =FV(taxa_mensal,qtd_anos*12,aporte*-1) -> 62853.015
B14: Dividendos Mensais? | C14: =C13*C12 -> 678.81256
B17: Cenários | D17: Dividendo
A18: 2 | B18: Quanto em 2 Anos? | C18: =FV(taxa_mensal,A18*12,aporte*-1) -> 20423.148 | D18: =C18*rendimento_carteira -> 122.53889
A19: 5 | B19: Quanto em 5 Anos? | C19: =FV(taxa_mensal,A19*12,aporte*-1) -> 62853.015 | D19: =C19*rendimento_carteira -> 377.11809
A20: 10 | B20: Quanto em 10 Anos? | C20: =FV(taxa_mensal,A20*12,aporte*-1) -> 182593.25 | D20: =C20*rendimento_carteira -> 1095.5595
A21: 20 | B21: Quanto em 20 Anos? | C21: =FV(taxa_mensal,A21*12,aporte*-1) -> 845286.74 | D21: =C21*rendimento_carteira -> 5071.7205
A22: 30 | B22: Quanto em 30 Anos? | C22: =FV(taxa_mensal,A22*12,aporte*-1) -> 3250428.6 | D22: =C22*rendimento_carteira -> 19502.572
B24: Perfil | C24: Agressivo | D24: selecione um perfil ao lado
B25: Valor a ser investido por mês | C25: =aporte -> 750
B27: TIPO DE FII | C27: Percentual Sugerido | D27: Valores
B28: PAPEL | C28: =IFERROR(VLOOKUP(tipo_perfil&"-"&B28,Suporte!A:D,4,0),0) -> 0.5 | D28: =C28*investimento -> 375
B29: TIJOLO | C29: =IFERROR(VLOOKUP(tipo_perfil&"-"&B29,Suporte!A:D,4,0),0) -> 0.1 | D29: =C29*investimento -> 75
B30: HÍBRIDOS | C30: =IFERROR(VLOOKUP(tipo_perfil&"-"&B30,Suporte!A:D,4,0),0) -> 0.05 | D30: =C30*investimento -> 37.5
B31: FOFS | C31: =IFERROR(VLOOKUP(tipo_perfil&"-"&B31,Suporte!A:D,4,0),0) -> 0.05 | D31: =C31*investimento -> 37.5
B32: DESENVOLVIMENTO | C32: =IFERROR(VLOOKUP(tipo_perfil&"-"&B32,Suporte!A:D,4,0),0) -> 0.2 | D32: =C32*investimento -> 150
B33: HOTELARIAS | C33: =IFERROR(VLOOKUP(tipo_perfil&"-"&B33,Suporte!A:D,4,0),0) -> 0.1 | D33: =C33*investimento -> 75

Sheet Suporte
A2: CHAVE | B2: Perfil | C2: TIPO DE FII | D2: %
A3: =B3&"-"&C3 -> Conservador-PAPEL | B3: Conservador | C3: PAPEL | D3: 0.3 | H3: Conservador | I3: 1
A4: =B4&"-"&C4 -> Conservador-TIJOLO | B4: Conservador | C4: TIJOLO | D4: 0.5 | H4: Moderado | I4: 2
A5: =B5&"-"&C5 -> Conservador-HÍBRIDOS | B5: Conservador | C5: HÍBRIDOS | D5: 0.1 | H5: Agressivo | I5: 3
A6: =B6&"-"&C6 -> Conservador-FOFS | B6: Conservador | C6: FOFS | D6: 0.1
A7: =B7&"-"&C7 -> Conservador-DESENVOLVIMENTO | B7: Conservador | C7: DESENVOLVIMENTO | D7: 0
A8: =B8&"-"&C8 -> Conservador-HOTELARIAS | B8: Conservador | C8: HOTELARIAS | D8: 0
A9: =B9&"-"&C9 -> Moderado-PAPEL | B9: Moderado | C9: PAPEL | D9: 0.32
A10: =B10&"-"&C10 -> Moderado-TIJOLO | B10: Moderado | C10: TIJOLO | D10: 0.35
A11: =B11&"-"&C11 -> Moderado-HÍBRIDOS | B11: Moderado | C11: HÍBRIDOS | D11: 0.08
A12: =B12&"-"&C12 -> Moderado-FOFS | B12: Moderado | C12: FOFS | D12: 0.05
A13: =B13&"-"&C13 -> Moderado-DESENVOLVIMENTO | B13: Moderado | C13: DESENVOLVIMENTO | D13: 0.1
A14: =B14&"-"&C14 -> Moderado-HOTELARIAS | B14: Moderado | C14: HOTELARIAS | D14: 0.1
A15: =B15&"-"&C15 -> Agressivo-PAPEL | B15: Agressivo | C15: PAPEL | D15: 0.5
A16: =B16&"-"&C16 -> Agressivo-TIJOLO | B16: Agressivo | C16: TIJOLO | D16: 0.1
A17: =B17&"-"&C17 -> Agressivo-HÍBRIDOS | B17: Agressivo | C17: HÍBRIDOS | D17: 0.05
... A20: =B20&"-"&C20 -> Agressivo-HOTELARIAS | B20: Agressivo | C20: HOTELARIAS | D20: 0.1
